aihcx/__init__.py
aihcx/cli.py
aihcx/client.py
aihcx/commands.py
aihcx-0.1.0.dist-info/METADATA
aihcx-0.1.0.dist-info/WHEEL
aihcx-0.1.0.dist-info/entry_points.txt
aihcx-0.1.0.dist-info/top_level.txt
aihcx-0.1.0.dist-info/RECORD
